MANIFEST.in
setup.py
xl-helper
xl_helper/Argh.py
xl_helper/Engine.py
xl_helper/FileUtils.py
xl_helper/Utils.py
xl_helper/XlHelperConfig.py
xl_helper/__init__.py
xl_helper.egg-info/PKG-INFO
xl_helper.egg-info/SOURCES.txt
xl_helper.egg-info/dependency_links.txt
xl_helper.egg-info/requires.txt
xl_helper.egg-info/top_level.txt
xl_helper/actions/Installer.py
xl_helper/actions/Server.py
xl_helper/actions/Uninstaller.py
xl_helper/actions/Upgrader.py
xl_helper/actions/__init__.py
xl_helper/artifacts/Cache.py
xl_helper/artifacts/Plugin.py
xl_helper/artifacts/PluginsSelection.py
xl_helper/artifacts/SemanticVersion.py
xl_helper/artifacts/__init__.py
xl_helper/artifacts/cli/DownloadsCliDist.py
xl_helper/artifacts/cli/__init__.py
xl_helper/artifacts/server/LocalServerDist.py
xl_helper/artifacts/server/RemoteServerDist.py
xl_helper/artifacts/server/ServerDist.py
xl_helper/artifacts/server/__init__.py
xl_helper/resources/.xl-helper.defaults
xl_helper/resources/__init__.py
xl_helper/resources/deployit.conf