Metadata-Version: 1.0
Name: xl-helper
Version: 1.0.5
Summary: XL Deploy helper
Home-page: http://xebialabs.com/
Author: Mike Kotsur
Author-email: mkotsur@xebialabs.com
License: UNKNOWN
Platform: UNKNOWN
